setup.py
bayesflare/__init__.py
bayesflare.egg-info/PKG-INFO
bayesflare.egg-info/SOURCES.txt
bayesflare.egg-info/dependency_links.txt
bayesflare.egg-info/requires.txt
bayesflare.egg-info/top_level.txt
bayesflare/data/__init__.py
bayesflare/data/data.py
bayesflare/finder/__init__.py
bayesflare/finder/find.py
bayesflare/inject/__init__.py
bayesflare/inject/inject.py
bayesflare/misc/__init__.py
bayesflare/misc/misc.py
bayesflare/models/__init__.py
bayesflare/models/model.py
bayesflare/noise/__init__.py
bayesflare/noise/noise.py
bayesflare/simulate/__init__.py
bayesflare/simulate/simulate.py
bayesflare/stats/__init__.py
bayesflare/stats/bayes.py
bayesflare/stats/general.c
bayesflare/stats/log_marg_amp_full.c
bayesflare/stats/thresholding.py