Metadata-Version: 1.1
Name: bayesflare
Version: 1.0.4
Summary: Python functions and classes implementing a Bayesian approach to flare finding.
Home-page: https://github.com/BayesFlare/bayesflare
Author: Matthew Pitkin, Daniel Williams
Author-email: matthew.pitkin@glasgow.ac.uk
License: UNKNOWN
Platform: UNKNOWN
Classifier: Development Status :: 5 - Production/Stable
Classifier: Intended Audience :: Science/Research
Classifier: License :: OSI Approved :: GNU General Public License (GPL)
Classifier: Operating System :: POSIX :: Linux
Classifier: Programming Language :: Python
Classifier: Programming Language :: C
Classifier: Natural Language :: English
Classifier: Topic :: Scientific/Engineering :: Astronomy
Classifier: Topic :: Scientific/Engineering :: Information Analysis
